CHANGES.rst
MANIFEST.in
README.rst
setup.py
src/bobo.py
src/boboserver.py
src/bobo.egg-info/PKG-INFO
src/bobo.egg-info/SOURCES.txt
src/bobo.egg-info/dependency_links.txt
src/bobo.egg-info/entry_points.txt
src/bobo.egg-info/not-zip-safe
src/bobo.egg-info/requires.txt
src/bobo.egg-info/top_level.txt